brusnika_airflow/__init__.py
brusnika_airflow/airflow_funcs.py
brusnika_airflow-0.0.7.dist-info/METADATA
brusnika_airflow-0.0.7.dist-info/WHEEL
brusnika_airflow-0.0.7.dist-info/top_level.txt
brusnika_airflow-0.0.7.dist-info/RECORD
