Metadata-Version: 2.1
Name: brusnika-airflow
Version: 0.0.7
Summary: This Python package contains a set of frequently used functions for using in DAGs.
Author-email: Aleksei Zhuravlev <a.zhuravlev@brusnika.ru>
Project-URL: Homepage, https://gitlab.brusnika.tech/erp/skm/etl/brusnika_airflow
Project-URL: Issues, https://gitlab.brusnika.tech/erp/skm/etl/brusnika_airflow/-/issues
Classifier: Programming Language :: Python :: 3
Classifier: License :: OSI Approved :: MIT License
Classifier: Operating System :: OS Independent
Requires-Python: >=3.8
Requires-Dist: pendulum
Requires-Dist: sqlalchemy
